crosspredict/.DS_Store
crosspredict/__init__.py
crosspredict/iterator.py
crosspredict/parameters.yml
crosspredict/__pycache__/__init__.cpython-310.pyc
crosspredict/__pycache__/__init__.cpython-312.pyc
crosspredict/__pycache__/iterator.cpython-310.pyc
crosspredict/__pycache__/iterator.cpython-312.pyc
crosspredict/crossval/__init__.py
crosspredict/crossval/_catboost.py
crosspredict/crossval/_crossval.py
crosspredict/crossval/_lightgbm.py
crosspredict/crossval/_xgboost.py
crosspredict/crossval/__pycache__/__init__.cpython-310.pyc
crosspredict/crossval/__pycache__/__init__.cpython-312.pyc
crosspredict/crossval/__pycache__/_catboost.cpython-310.pyc
crosspredict/crossval/__pycache__/_catboost.cpython-312.pyc
crosspredict/crossval/__pycache__/_crossval.cpython-310.pyc
crosspredict/crossval/__pycache__/_crossval.cpython-312.pyc
crosspredict/crossval/__pycache__/_lightgbm.cpython-310.pyc
crosspredict/crossval/__pycache__/_lightgbm.cpython-312.pyc
crosspredict/crossval/__pycache__/_xgboost.cpython-310.pyc
crosspredict/crossval/__pycache__/_xgboost.cpython-312.pyc
crosspredict/nodes/__init__.py
crosspredict/nodes/_nodes.py
crosspredict/nodes/__pycache__/__init__.cpython-310.pyc
crosspredict/nodes/__pycache__/_nodes.cpython-310.pyc
crosspredict/report_binary/__init__.py
crosspredict/report_binary/_curves.py
crosspredict/report_binary/_report_binary.py
crosspredict/report_binary/__pycache__/__init__.cpython-310.pyc
crosspredict/report_binary/__pycache__/__init__.cpython-312.pyc
crosspredict/report_binary/__pycache__/_curves.cpython-310.pyc
crosspredict/report_binary/__pycache__/_curves.cpython-312.pyc
crosspredict/report_binary/__pycache__/_report_binary.cpython-310.pyc
crosspredict/report_binary/__pycache__/_report_binary.cpython-312.pyc
crosspredict/target_encoder/__init__.py
crosspredict/target_encoder/_crosstargetencoder.py
crosspredict/target_encoder/_target_encoder.py
tests/__init__.py
tests/conftest.py
tests/test_binary.py
tests/test_iterator.py
crosspredict-1.1.11.dist-info/LICENSE
crosspredict-1.1.11.dist-info/METADATA
crosspredict-1.1.11.dist-info/WHEEL
crosspredict-1.1.11.dist-info/top_level.txt
crosspredict-1.1.11.dist-info/RECORD
