Metadata-Version: 2.1
Name: crosspredict
Version: 1.1.11
Summary: package for easy crossvalidation
Author: Vladislav Boyadzhi
Author-email: vladislav.boyadzhi@gmail.com
Classifier: Programming Language :: Python :: 3
Classifier: License :: OSI Approved :: MIT License
Classifier: Operating System :: OS Independent
License-File: LICENSE
Requires-Dist: catboost >=1.2.3
Requires-Dist: category-encoders >=2.6.3
Requires-Dist: hyperopt >=0.2.7
Requires-Dist: lightgbm >=4.3.0
Requires-Dist: numpy >=1.26.4
Requires-Dist: pandas >=2.2.1
Requires-Dist: pyyaml ==5.3
Requires-Dist: seaborn >=0.13.2
Requires-Dist: shap >=0.45.0
Requires-Dist: tabulate >=0.9.0
Requires-Dist: xgboost >=2.0.3
Requires-Dist: matplotlib >=3.8.4
Requires-Dist: matplotlib-inline >=0.1.6
Requires-Dist: scikit-learn >=1.4.1.post1
Requires-Dist: requests >=2.31.0
Requires-Dist: pytest ==8.1.1
Requires-Dist: pytest-print ==1.0.0
